{
    "homepage": "https://github.com/influxdata/telegraf",
    "description": "The plugin-driven server agent for collecting & reporting metrics",
    "version": "1.10.4",
    "license": "MIT",
    "architecture": {
        "32bit": {
            "url": "https://dl.influxdata.com/telegraf/releases/telegraf-1.10.4_windows_i386.zip",
            "hash": "f263d22afc777e38d1592a288811ece2aa9e3449a41ec046939ce61dd85b46e8"
        },
        "64bit": {
            "url": "https://dl.influxdata.com/telegraf/releases/telegraf-1.10.4_windows_amd64.zip",
            "hash": "038bd8e3bd294a154ec8d4d858813d6bce41527c4b19deba59bb800aa7acda70"
        }
    },
    "extract_dir": "telegraf",
    "bin": [
        [
            "telegraf.exe",
            "telegraf",
            "--config $dir\\telegraf.conf"
        ]
    ],
    "persist": "telegraf.conf",
    "checkver": {
        "github": "https://github.com/influxdata/telegraf"
    },
    "autoupdate": {
        "architecture": {
            "32bit": {
                "url": "https://dl.influxdata.com/telegraf/releases/telegraf-$version_windows_i386.zip"
            },
            "64bit": {
                "url": "https://dl.influxdata.com/telegraf/releases/telegraf-$version_windows_amd64.zip"
            }
        }
    }
}
